star_jwt/__init__.py
star_jwt/backend.py
star_jwt-0.4.0.dist-info/LICENSE.md
star_jwt-0.4.0.dist-info/METADATA
star_jwt-0.4.0.dist-info/WHEEL
star_jwt-0.4.0.dist-info/top_level.txt
star_jwt-0.4.0.dist-info/RECORD
