Metadata-Version: 2.1
Name: star-jwt
Version: 0.4.0
Summary: JSON Web Token authenticator backend for Starlette's authentication system.
Home-page: https://github.com/retnikt/starlette_jwt
Author: retnikt
Author-email: _@retnikt.uk
License: UNKNOWN
Platform: UNKNOWN
Classifier: Development Status :: 3 - Alpha
Classifier: Programming Language :: Python :: 3.8
Classifier: License :: OSI Approved :: GNU Affero General Public License v3
Classifier: Operating System :: OS Independent
Classifier: Environment :: Web Environment
Classifier: Intended Audience :: Developers
Classifier: Natural Language :: English
Classifier: Topic :: Internet :: WWW/HTTP
Classifier: Typing :: Typed
Requires-Python: >=3.8
Requires-Dist: starlette (>=0.9.6)
Requires-Dist: pyjwt (>=1.0.1)
